{
  "layout": [
    {
      "i": "pieChart-1734744233889",
      "x": 0,
      "y": 0,
      "w": 4,
      "h": 3,
      "type": "pieChart",
      "data": [
        {
          "name": "Ms",
          "value": 178
        },
        {
          "name": "Mr",
          "value": 172
        },
        {
          "name": "Dr",
          "value": 159
        },
        {
          "name": "Honorable",
          "value": 191
        },
        {
          "name": "Mrs",
          "value": 161
        },
        {
          "name": "Rev",
          "value": 149
        }
      ],
      "title": "Título no definido",
      "subTitle": "",
      "description": "",
      "moved": false,
      "static": false
    }
  ]
}