[
  {
      "name": "ESS SI Ejecutiva",
      "isSublist": false,
      "to": "/",
      "logo": "bi bi-dash-circle"
  },
  
  {
    "name": "Operaciones",
    "isSublist": true,
    "sublist": [
      {
        "name": "Transacciones",
        "to": "/transactions"
      },
      {
        "name": "Usuarios",
        "to": "/users"
      },
      {
        "name": "Procesos",
        "to": "/process"
      }
    ],
    "logo": "bi bi-info-circle"
  },
  {
      "Separado": "Marketing",
      "isSeperador" : true
  },
  {
    "name": "Marketing",
    "isSublist": true,
    "sublist": [
      {
        "name": "Pag100",
        "to": "/Pag100"
      },
      {
        "name": "Pag101",
        "to": "/Pag101"
      },
      {
        "name": "Pag102",
        "to": "/Pag102"
      }
    ],
    "logo": "bi bi-info-circle"
  }

]